live_questions/__init__.py
live_questions/console.py
live_questions/main.py
live_questions/ngrok.py
live_questions/settings.py
live_questions/static/android-chrome-192x192.png
live_questions/static/android-chrome-512x512.png
live_questions/static/apple-touch-icon.png
live_questions/static/favicon-16x16.png
live_questions/static/favicon-32x32.png
live_questions/static/favicon.ico
live_questions/static/site.webmanifest
live_questions/storage.py
live_questions/templates/home.html
live_questions/web.py
live_questions-0.1.1.dist-info/LICENSE
live_questions-0.1.1.dist-info/METADATA
live_questions-0.1.1.dist-info/WHEEL
live_questions-0.1.1.dist-info/entry_points.txt
live_questions-0.1.1.dist-info/RECORD
